lorem_gen/generator.py
lorem_gen/init.py
lorem_gen-0.1.1.dist-info/licenses/LICENSE
lorem_gen-0.1.1.dist-info/METADATA
lorem_gen-0.1.1.dist-info/WHEEL
lorem_gen-0.1.1.dist-info/entry_points.txt
lorem_gen-0.1.1.dist-info/top_level.txt
lorem_gen-0.1.1.dist-info/RECORD
