Metadata-Version: 2.4
Name: lorem_gen
Version: 0.1.1
Summary: Generate Lorem Ipsum placeholder text via CLI or Python API
Author-email: devvyyxyz <devvyyxyz@devvyy.xyz>
License: MIT
Project-URL: Homepage, https://github.com/devvyyxyz/lorem_gen
Project-URL: Repository, https://github.com/devvyyxyz/lorem_gen
Project-URL: Documentation, https://github.com/devvyyxyz/lorem_gen
Classifier: Programming Language :: Python :: 3
Classifier: Programming Language :: Python :: 3.8
Classifier: License :: OSI Approved :: MIT License
Classifier: Operating System :: OS Independent
Requires-Python: >=3.8
License-File: LICENSE
Dynamic: license-file
